pynuvo/__init__.py
pynuvo-0.2.dist-info/DESCRIPTION.rst
pynuvo-0.2.dist-info/METADATA
pynuvo-0.2.dist-info/RECORD
pynuvo-0.2.dist-info/WHEEL
pynuvo-0.2.dist-info/metadata.json
pynuvo-0.2.dist-info/top_level.txt
