Metadata-Version: 2.0
Name: pynuvo
Version: 0.2
Summary: Python API for talking to Nuvo multi zone amplifier
Home-page: https://github.com/ejonesnospam/pynuvo
Author: ejonesnospam
Author-email: ejonesnospam@gmail.com
License: UNKNOWN
Platform: UNKNOWN
Classifier: Programming Language :: Python :: 3
Classifier: License :: OSI Approved :: MIT License
Classifier: Operating System :: OS Independent
Requires-Dist: pyserial (>=3.4)
